rxbp/__init__.py
rxbp/abc.py
rxbp/cancellable.py
rxbp/exceptions.py
rxbp/py.typed
rxbp/state.py
rxbp/typing.py
rxbp/flowable/__init__.py
rxbp/flowable/flowable.py
rxbp/flowable/flowable.pyi
rxbp/flowable/from_.py
rxbp/flowable/from_.pyi
rxbp/flowable/init.py
rxbp/flowable/to.py
rxbp/flowabletree/__init__.py
rxbp/flowabletree/assignweightmixin.py
rxbp/flowabletree/from_.py
rxbp/flowabletree/nodes.py
rxbp/flowabletree/observer.py
rxbp/flowabletree/subscribe.py
rxbp/flowabletree/subscribeargs.py
rxbp/flowabletree/subscription.py
rxbp/flowabletree/subscriptionresult.py
rxbp/flowabletree/to.py
rxbp/flowabletree/operations/__init__.py
rxbp/flowabletree/operations/accumulate.py
rxbp/flowabletree/operations/defaultifempty.py
rxbp/flowabletree/operations/doaction.py
rxbp/flowabletree/operations/filter.py
rxbp/flowabletree/operations/map.py
rxbp/flowabletree/operations/reduce.py
rxbp/flowabletree/operations/repeatfirst.py
rxbp/flowabletree/operations/skipwhile.py
rxbp/flowabletree/operations/takewhile.py
rxbp/flowabletree/operations/tolist.py
rxbp/flowabletree/operations/buffer/flowable.py
rxbp/flowabletree/operations/buffer/observer.py
rxbp/flowabletree/operations/buffer/states.py
rxbp/flowabletree/operations/buffer/statetransitions.py
rxbp/flowabletree/operations/flatmap/__init__.py
rxbp/flowabletree/operations/flatmap/cancellable.py
rxbp/flowabletree/operations/flatmap/flowable.py
rxbp/flowabletree/operations/flatmap/innerobserver.py
rxbp/flowabletree/operations/flatmap/observer.py
rxbp/flowabletree/operations/flatmap/sharedmemory.py
rxbp/flowabletree/operations/flatmap/states.py
rxbp/flowabletree/operations/flatmap/statetransitions.py
rxbp/flowabletree/operations/merge/__init__.py
rxbp/flowabletree/operations/merge/cancellable.py
rxbp/flowabletree/operations/merge/flowable.py
rxbp/flowabletree/operations/merge/observer.py
rxbp/flowabletree/operations/merge/sharedmemory.py
rxbp/flowabletree/operations/merge/states.py
rxbp/flowabletree/operations/merge/statetransitions.py
rxbp-0.1.0.dist-info/METADATA
rxbp-0.1.0.dist-info/WHEEL
rxbp-0.1.0.dist-info/licenses/LICENSE
rxbp-0.1.0.dist-info/RECORD
