Metadata-Version: 2.4
Name: rxbp
Version: 0.1.0
Summary: A library that integrates *backpressure* into the *Observable* via *Flowables*. 
Project-URL: Homepage, https://github.com/MichaelSchneeberger/rxbp
Author-email: Michael Schneeberger <michael.schneeb@hotmail.com>
License-File: LICENSE
Requires-Python: >=3.12
Requires-Dist: continuationmonad>=0.0.3
Requires-Dist: dataclassabc>=0.0.15
Requires-Dist: donotation>=0.0.10
Requires-Dist: reactivex>=4.0.0
